<?xml version="1.0"?>
<opencv_storage>
<stage14>
  <maxWeakCount>8</maxWeakCount>
  <stageThreshold>-1.3394373655319214e+00</stageThreshold>
  <weakClassifiers>
    <_>
      <internalNodes>
        0 -1 757 -1.4185488689690828e-03</internalNodes>
      <leafValues>
        2.2807016968727112e-01 -6.7741936445236206e-01</leafValues></_>
    <_>
      <internalNodes>
        0 -1 21543 3.5590529441833496e-02</internalNodes>
      <leafValues>
        -4.2136871814727783e-01 4.4183918833732605e-01</leafValues></_>
    <_>
      <internalNodes>
        0 -1 7545 2.7889985358342528e-04</internalNodes>
      <leafValues>
        2.8329131007194519e-01 -5.8694714307785034e-01</leafValues></_>
    <_>
      <internalNodes>
        0 -1 65742 3.1343282898887992e-04</internalNodes>
      <leafValues>
        3.3477109670639038e-01 -5.4250401258468628e-01</leafValues></_>
    <_>
      <internalNodes>
        0 -1 54046 3.4135763416998088e-04</internalNodes>
      <leafValues>
        -3.9596799015998840e-01 4.3659719824790955e-01</leafValues></_>
    <_>
      <internalNodes>
        0 -1 61442 -2.3157179821282625e-03</internalNodes>
      <leafValues>
        7.2085708379745483e-01 -2.5725632905960083e-01</leafValues></_>
    <_>
      <internalNodes>
        0 -1 206 -8.2506015896797180e-03</internalNodes>
      <leafValues>
        5.1666873693466187e-01 -4.0896412730216980e-01</leafValues></_>
    <_>
      <internalNodes>
        0 -1 66947 5.5747735314071178e-04</internalNodes>
      <leafValues>
        2.4818675220012665e-01 -7.5059700012207031e-01</leafValues></_></weakClassifiers></stage14>
</opencv_storage>
