<?xml version="1.0"?>
<opencv_storage>
<stage10>
  <maxWeakCount>5</maxWeakCount>
  <stageThreshold>-1.3943289518356323e+00</stageThreshold>
  <weakClassifiers>
    <_>
      <internalNodes>
        0 -1 185466 4.1191810742020607e-03</internalNodes>
      <leafValues>
        -6.0801780223846436e-01 4.8344370722770691e-01</leafValues></_>
    <_>
      <internalNodes>
        0 -1 70621 3.2937589567154646e-03</internalNodes>
      <leafValues>
        -8.0719470977783203e-01 3.4669893980026245e-01</leafValues></_>
    <_>
      <internalNodes>
        0 -1 101886 -1.2360848486423492e-03</internalNodes>
      <leafValues>
        5.0959044694900513e-01 -5.5006110668182373e-01</leafValues></_>
    <_>
      <internalNodes>
        0 -1 150199 -1.4810170978307724e-04</internalNodes>
      <leafValues>
        -8.8074880838394165e-01 3.0299827456474304e-01</leafValues></_>
    <_>
      <internalNodes>
        0 -1 183506 2.1906523033976555e-04</internalNodes>
      <leafValues>
        2.6794636249542236e-01 -9.6651750802993774e-01</leafValues></_></weakClassifiers></stage10>
</opencv_storage>
